CoverGPT/__init_.py
CoverGPT/__main__.py
CoverGPT/cover.cls
CoverGPT/gptex.py
CoverGPT/gui.py
CoverGPT/template.tex
CoverGPT/OpenFonts/deedy_resume-openfont.xtx
CoverGPT/OpenFonts/signature.png
CoverGPT/OpenFonts/fonts/lato/Lato-Bla.ttf
CoverGPT/OpenFonts/fonts/lato/Lato-BlaIta.ttf
CoverGPT/OpenFonts/fonts/lato/Lato-Bol.ttf
CoverGPT/OpenFonts/fonts/lato/Lato-BolIta.ttf
CoverGPT/OpenFonts/fonts/lato/Lato-Hai.ttf
CoverGPT/OpenFonts/fonts/lato/Lato-HaiIta.ttf
CoverGPT/OpenFonts/fonts/lato/Lato-Lig.ttf
CoverGPT/OpenFonts/fonts/lato/Lato-LigIta.ttf
CoverGPT/OpenFonts/fonts/lato/Lato-Reg.ttf
CoverGPT/OpenFonts/fonts/lato/Lato-RegIta.ttf
CoverGPT/OpenFonts/fonts/raleway/Raleway-Bold.otf
CoverGPT/OpenFonts/fonts/raleway/Raleway-ExtraBold.otf
CoverGPT/OpenFonts/fonts/raleway/Raleway-ExtraLight.otf
CoverGPT/OpenFonts/fonts/raleway/Raleway-Heavy.otf
CoverGPT/OpenFonts/fonts/raleway/Raleway-Light.otf
CoverGPT/OpenFonts/fonts/raleway/Raleway-Medium.otf
CoverGPT/OpenFonts/fonts/raleway/Raleway-Regular.otf
CoverGPT/OpenFonts/fonts/raleway/Raleway-SemiBold.otf
CoverGPT/OpenFonts/fonts/raleway/Raleway-Thin.otf
CoverGPT-1.3.1.dist-info/LICENSE
CoverGPT-1.3.1.dist-info/METADATA
CoverGPT-1.3.1.dist-info/WHEEL
CoverGPT-1.3.1.dist-info/top_level.txt
CoverGPT-1.3.1.dist-info/RECORD
